jupyter_cli/__init__.py
jupyter_cli/cli.py
jupyter_cli/client.py
jupyter_cli/daemon.py
jupyter_cli/notebook.py
jupyter_cli/skill/SKILL.md
jupyter_cli/skill/__init__.py
tests/__init__.py
tests/test_basic.py
tests/test_jupyter_cli.py
jupyter_cli-0.1.8.dist-info/METADATA
jupyter_cli-0.1.8.dist-info/WHEEL
jupyter_cli-0.1.8.dist-info/entry_points.txt
jupyter_cli-0.1.8.dist-info/top_level.txt
jupyter_cli-0.1.8.dist-info/RECORD
