Metadata-Version: 2.4
Name: jupyter-cli
Version: 0.1.8
Summary: Programmatic Jupyter cell execution with persistent kernels
Author: Andrew Ting
License-Expression: MIT
Project-URL: Homepage, https://github.com/andrewting19/jupyter-cli
Project-URL: Repository, https://github.com/andrewting19/jupyter-cli
Project-URL: Issues, https://github.com/andrewting19/jupyter-cli/issues
Keywords: jupyter,notebook,cli,kernel,execution,llm,agent
Classifier: Development Status :: 4 - Beta
Classifier: Intended Audience :: Developers
Classifier: Programming Language :: Python :: 3
Classifier: Programming Language :: Python :: 3.8
Classifier: Programming Language :: Python :: 3.9
Classifier: Programming Language :: Python :: 3.10
Classifier: Programming Language :: Python :: 3.11
Classifier: Programming Language :: Python :: 3.12
Requires-Python: >=3.8
Requires-Dist: jupyter_client>=7.0.0
Requires-Dist: nbformat>=5.0.0
Requires-Dist: click>=8.0.0
Requires-Dist: ipykernel>=6.0.0
Provides-Extra: dev
Requires-Dist: pytest>=7.0.0; extra == "dev"
